gamebot_lite/__init__.py
gamebot_lite/__main__.py
gamebot_lite/catalog.py
gamebot_lite/client.py
gamebot_lite/data/gamebot.sqlite
gamebot_lite/data/manifest.json
gamebot_lite-0.1.5.dist-info/licenses/LICENSE
gamebot_lite-0.1.5.dist-info/METADATA
gamebot_lite-0.1.5.dist-info/WHEEL
gamebot_lite-0.1.5.dist-info/top_level.txt
gamebot_lite-0.1.5.dist-info/RECORD
