Metadata-Version: 2.4
Name: gamebot-lite
Version: 0.1.5
Summary: Lightweight Survivor data snapshot (SQLite)
Author: Gamebot Team
Project-URL: Homepage, https://github.com/mgrody1/Gamebot
Project-URL: Repository, https://github.com/mgrody1/Gamebot
Project-URL: Issues, https://github.com/mgrody1/Gamebot/issues
Project-URL: Documentation, https://github.com/mgrody1/Gamebot/blob/main/docs/analyst_guide.md
Requires-Python: >=3.8
License-File: LICENSE
Requires-Dist: pandas
Provides-Extra: duckdb
Requires-Dist: duckdb; extra == "duckdb"
Dynamic: license-file
